springpy/__init__.py
springpy/main.py
springpy-1.0.0.dist-info/LICENSE
springpy-1.0.0.dist-info/METADATA
springpy-1.0.0.dist-info/WHEEL
springpy-1.0.0.dist-info/top_level.txt
springpy-1.0.0.dist-info/RECORD
