Metadata-Version: 2.1
Name: springpy
Version: 1.0.0
Summary: Distance Matrix Visualizer in Python
Home-page: https://github.com/kiwirafe/springpy
Author: kiwirafe
Author-email: kiwirafe@gmail.com
Project-URL: Github, https://github.com/kiwirafe/springpy
Classifier: Programming Language :: Python :: 3
Classifier: License :: OSI Approved :: MIT License
Classifier: Operating System :: OS Independent
Requires-Python: >=3.4
License-File: LICENSE
Requires-Dist: matplotlib
